advance_common/__init__.py
advance_common/custom_mavlink_frame.py
advance_common/mavlink_logger.py
advance_common/messages.proto
advance_common/messages_pb2.py
advance_common/setup_logging.py
advance_common-1.3.1.dist-info/METADATA
advance_common-1.3.1.dist-info/WHEEL
advance_common-1.3.1.dist-info/RECORD
