Metadata-Version: 2.1
Name: advance-common
Version: 1.3.1
Summary: 
Author: Szymon-SR
Author-email: srszymonsr@gmail.com
Requires-Python: >=3.6.9,<4.0.0
Classifier: Programming Language :: Python :: 3
Classifier: Programming Language :: Python :: 3.7
Classifier: Programming Language :: Python :: 3.8
Classifier: Programming Language :: Python :: 3.9
Classifier: Programming Language :: Python :: 3.10
Classifier: Programming Language :: Python :: 3.11
Requires-Dist: protobuf (==3.19.4)
Requires-Dist: pymavlink (>=2.4.15,<=2.4.27)
Requires-Dist: pyserial (>=3.5,<4.0)
